{
  "extracted_at": "20250602_162725",
  "tree": [
    {
      "node_type": "L0",
      "name": "Webáruház",
      "url": "https://www.samsung.com/hu/offer/",
      "analytics": "shop",
      "url_name": "Webáruház",
      "children": [
        {
          "node_type": "L1_Product",
          "name": "Galaxy S25 Ultra",
          "url": "https://www.samsung.com/hu/smartphones/galaxy-s25-ultra/buy/",
          "analytics": "galaxy s25 ultra",
          "url_name": "Galaxy S25 Ultra",
          "children": []
        },
        {
          "node_type": "L1_Product",
          "name": "Galaxy S25 | S25+",
          "url": "https://www.samsung.com/hu/smartphones/galaxy-s25/buy/",
          "analytics": "galaxy s25 | s25 plus",
          "url_name": "Galaxy S25 | S25+",
          "children": []
        },
        {
          "node_type": "L1_Product",
          "name": "Galaxy Fold6",
          "url": "https://www.samsung.com/hu/smartphones/galaxy-z-fold6/buy/",
          "analytics": "galaxy fold6",
          "url_name": "Galaxy Fold6",
          "children": []
        },
        {
          "node_type": "L1_Product",
          "name": "Galaxy Flip6",
          "url": "https://www.samsung.com/hu/smartphones/galaxy-z-flip6/buy/",
          "analytics": "galaxy flip6",
          "url_name": "Galaxy Flip6",
          "children": []
        },
        {
          "node_type": "L1_Product",
          "name": "Galaxy A56 5G",
          "url": "https://www.samsung.com/hu/smartphones/galaxy-a/galaxy-a56-5g/buy/?modelCode=SM-A566BZACEUE",
          "analytics": "galaxy a56 5g",
          "url_name": "Galaxy A56 5G",
          "children": []
        },
        {
          "node_type": "L1_Product",
          "name": "Galaxy Tab S10 Series",
          "url": "https://www.samsung.com/hu/tablets/galaxy-tab-s10/buy/?modelCode=SM-X920NZAREUE",
          "analytics": "galaxy tab s10 series",
          "url_name": "Galaxy Tab S10 Series",
          "children": []
        },
        {
          "node_type": "L1_Product",
          "name": "Galaxy Watch Ultra",
          "url": "https://www.samsung.com/hu/watches/galaxy-watch/galaxy-watch-ultra-titanium-gray-lte-sm-l705fdaaeue/",
          "analytics": "galaxy watch ultra",
          "url_name": "Galaxy Watch Ultra",
          "children": []
        },
        {
          "node_type": "L1_Product",
          "name": "Galaxy Buds3 Pro",
          "url": "https://www.samsung.com/hu/audio-sound/galaxy-buds/galaxy-buds3-pro-silver-sm-r630nzaaeue/",
          "analytics": "galaxy buds3 pro",
          "url_name": "Galaxy Buds3 Pro",
          "children": []
        },
        {
          "node_type": "L1_Product",
          "name": "Galaxy Book5 Pro",
          "url": "https://www.samsung.com/uk/computers/galaxy-book/galaxy-book5-pro/buy/?modelCode=NP960XHA-KG2UK",
          "analytics": "Galaxy Book5 Pro",
          "url_name": "Galaxy Book5 Pro",
          "children": []
        },
        {
          "node_type": "L1_Product",
          "name": "Neo QLED 8K TV",
          "url": "https://www.samsung.com/hu/tvs/qled-tv/qn990f-65-inch-neo-qled-8k-mini-led-smart-tv-qe65qn990ftxxh/",
          "analytics": "neo qled 8k tv",
          "url_name": "Neo QLED 8K TV",
          "children": []
        },
        {
          "node_type": "L1_Product",
          "name": "The Frame Pro",
          "url": "https://www.samsung.com/hu/lifestyle-tvs/the-frame/ls03fw-65-inch-black-qe65ls03fwuxxh/",
          "analytics": "the frame pro",
          "url_name": "The Frame Pro",
          "children": []
        },
        {
          "node_type": "L1_Product",
          "name": "Q-series Soundbar",
          "url": "https://www.samsung.com/hu/audio-devices/soundbar/q990f-black-hw-q990f-en/",
          "analytics": "q-series soundbar",
          "url_name": "Q-series Soundbar",
          "children": []
        },
        {
          "node_type": "L1_Product",
          "name": "Odyssey OLED G8",
          "url": "https://www.samsung.com/hu/monitors/gaming/odyssey-oled-g8-g81sf-32-inch-240hz-oled-uhd-ls32fg810suxen/",
          "analytics": "odyssey oled g8",
          "url_name": "Odyssey OLED G8",
          "children": []
        },
        {
          "node_type": "L1_Product",
          "name": "Samsung Bespoke SpaceMax™",
          "url": "https://www.samsung.com/uk/refrigerators/bottom-mount-freezer/bottom-mount-freezer-with-smartthings-ai-energy-mo-387l-black-rb38c607ab1-eu/",
          "analytics": "Samsung Bespoke SpaceMax™",
          "url_name": "Samsung Bespoke SpaceMax™",
          "children": []
        },
        {
          "node_type": "L1_Product",
          "name": "Samsung Series 8 AI Energy",
          "url": "https://www.samsung.com/hu/washers-and-dryers/washing-machines/ww7000d-front-loading-smartthings-ai-energy-made-a-20-percent-extra-energy-efficiency-ai-ecobubble-11kg-black-ww11db7b34gbu4/",
          "analytics": "samsung series 8 ai energy",
          "url_name": "Samsung Series 8 AI Energy",
          "children": []
        },
        {
          "node_type": "L1_Banner",
          "name": "Miért vásárolj a Samsungnál?",
          "url": "https://www.samsung.com/hu/offer/why-buy-from-samsung",
          "analytics": "why buy direct",
          "url_name": "Miért vásárolj a Samsungnál?",
          "children": []
        },
        {
          "node_type": "L1_Banner",
          "name": "Shop App",
          "url": "https://www.samsung.com/hu/apps/samsung-shop-app/",
          "analytics": "shop app",
          "url_name": "Shop App",
          "children": []
        },
        {
          "node_type": "L1_Banner",
          "name": "Készülékváltás",
          "url": "https://www.samsung.com/hu/offer/trade-up/",
          "analytics": "trade-up",
          "url_name": "Készülékváltás",
          "children": []
        },
        {
          "node_type": "L1_Banner",
          "name": "SmartThings",
          "url": "https://www.samsung.com/hu/smartthings/",
          "analytics": "smartthings",
          "url_name": "SmartThings",
          "children": []
        },
        {
          "node_type": "L1_Banner",
          "name": "Fedezd fel az AI-t",
          "url": "https://www.samsung.com/hu/ai-products/",
          "analytics": "discover ai",
          "url_name": "Fedezd fel az AI-t",
          "children": []
        },
        {
          "node_type": "L1_Banner",
          "name": "Tanulói webáruház",
          "url": "https://www.samsung.com/hu/students-offers/",
          "analytics": "for student & youth",
          "url_name": "Tanulói webáruház",
          "children": []
        },
        {
          "node_type": "L1_Banner",
          "name": "Készülékbeszámítás",
          "url": "https://www.samsung.com/hu/offer/mobile-trade-in/",
          "analytics": "trade-in",
          "url_name": "Készülékbeszámítás",
          "children": []
        }
      ]
    },
    {
      "node_type": "L0",
      "name": "Mobil",
      "url": "https://www.samsung.com/hu/smartphones/all-smartphones/",
      "analytics": "mobile",
      "url_name": "Mobil",
      "children": [
        {
          "node_type": "L1_Product",
          "name": "Galaxy okostelefonok",
          "url": "https://www.samsung.com/hu/smartphones/all-smartphones/",
          "analytics": "galaxy smartphone",
          "url_name": "Galaxy okostelefonok",
          "children": []
        },
        {
          "node_type": "L1_Product",
          "name": "Galaxy Tab",
          "url": "https://www.samsung.com/hu/tablets/all-tablets/",
          "analytics": "galaxy tab",
          "url_name": "Galaxy Tab",
          "children": []
        },
        {
          "node_type": "L1_Product",
          "name": "Galaxy Book",
          "url": "https://www.samsung.com/uk/computers/all-computers/?galaxy-book-ultra+galaxy-book-pro-360+galaxy-book-pro+14i04+14i05+14i07",
          "analytics": "galaxy  book",
          "url_name": "Galaxy Book",
          "children": []
        },
        {
          "node_type": "L1_Product",
          "name": "Galaxy Watch",
          "url": "https://www.samsung.com/hu/watches/all-watches/",
          "analytics": "galaxy watch",
          "url_name": "Galaxy Watch",
          "children": []
        },
        {
          "node_type": "L1_Product",
          "name": "Galaxy Buds",
          "url": "https://www.samsung.com/hu/audio-sound/all-audio-sound/",
          "analytics": "galaxy buds",
          "url_name": "Galaxy Buds",
          "children": []
        },
        {
          "node_type": "L1_Product",
          "name": "Galaxy Ring",
          "url": "https://www.samsung.com/hu/rings/all-rings/",
          "analytics": "galaxy ring",
          "url_name": "Galaxy Ring",
          "children": []
        },
        {
          "node_type": "L1_Product",
          "name": "Galaxy tartozékok",
          "url": "https://www.samsung.com/hu/mobile-accessories/all-mobile-accessories/",
          "analytics": "galaxy accessories",
          "url_name": "Galaxy tartozékok",
          "children": []
        },
        {
          "node_type": "L1_Product",
          "name": "Certified Renewed",
          "url": "https://www.samsung.com/uk/certified-re-newed-phones/",
          "analytics": "certified renewed",
          "url_name": "Certified Renewed",
          "children": []
        },
        {
          "node_type": "L1_Banner",
          "name": "Fedezd fel a mobil eszközöket",
          "url": "https://www.samsung.com/hu/mobile/",
          "analytics": "discover mobile",
          "url_name": "Fedezd fel a mobil eszközöket",
          "children": []
        },
        {
          "node_type": "L1_Banner",
          "name": "Galaxy AI",
          "url": "https://www.samsung.com/hu/galaxy-ai/",
          "analytics": "galaxy ai",
          "url_name": "Galaxy AI",
          "children": []
        },
        {
          "node_type": "L1_Banner",
          "name": "One UI",
          "url": "https://www.samsung.com/hu/one-ui/",
          "analytics": "one ui",
          "url_name": "One UI",
          "children": []
        },
        {
          "node_type": "L1_Banner",
          "name": "Samsung Health",
          "url": "https://www.samsung.com/hu/apps/samsung-health/",
          "analytics": "samsung health",
          "url_name": "Samsung Health",
          "children": []
        },
        {
          "node_type": "L1_Banner",
          "name": "Appok és szolgáltatások",
          "url": "https://www.samsung.com/hu/apps/",
          "analytics": "apps and service",
          "url_name": "Appok és szolgáltatások",
          "children": []
        },
        {
          "node_type": "L1_Banner",
          "name": "Miért a Galaxy?",
          "url": "https://www.samsung.com/hu/mobile/why-galaxy/",
          "analytics": "why galaxy",
          "url_name": "Miért a Galaxy?",
          "children": []
        },
        {
          "node_type": "L1_Banner",
          "name": "Válts Galaxyra!",
          "url": "https://www.samsung.com/hu/mobile/switch-to-galaxy/",
          "analytics": "switch to galaxy",
          "url_name": "Válts Galaxyra!",
          "children": []
        },
        {
          "node_type": "L1_Banner",
          "name": "Készülékbeszámítás",
          "url": "https://www.samsung.com/hu/offer/mobile-trade-in/",
          "analytics": "samsung trade-in",
          "url_name": "Készülékbeszámítás",
          "children": []
        }
      ]
    },
    {
      "node_type": "L0",
      "name": "TV & AV",
      "url": "https://www.samsung.com/hu/tvs/all-tvs/",
      "analytics": "tv and av",
      "url_name": "TV & AV",
      "children": [
        {
          "node_type": "L1_Product",
          "name": "Neo QLED",
          "url": "https://www.samsung.com/hu/tvs/neo-qled-tv/",
          "analytics": "neo qled",
          "url_name": "Neo QLED",
          "children": []
        },
        {
          "node_type": "L1_Product",
          "name": "OLED",
          "url": "https://www.samsung.com/hu/tvs/oled-tv/",
          "analytics": "oled",
          "url_name": "OLED",
          "children": []
        },
        {
          "node_type": "L1_Product",
          "name": "QLED",
          "url": "https://www.samsung.com/hu/tvs/qled-tv/",
          "analytics": "qled",
          "url_name": "QLED",
          "children": []
        },
        {
          "node_type": "L1_Product",
          "name": "Crystal UHD",
          "url": "https://www.samsung.com/hu/tvs/crystal-uhd-tv/",
          "analytics": "crystal uhd",
          "url_name": "Crystal UHD",
          "children": []
        },
        {
          "node_type": "L1_Product",
          "name": "The Frame",
          "url": "https://www.samsung.com/hu/lifestyle-tvs/the-frame/",
          "analytics": "the frame",
          "url_name": "The Frame",
          "children": []
        },
        {
          "node_type": "L1_Product",
          "name": "The Serif",
          "url": "https://www.samsung.com/hu/lifestyle-tvs/the-serif/",
          "analytics": "the serif",
          "url_name": "The Serif",
          "children": []
        },
        {
          "node_type": "L1_Product",
          "name": "The Terrace",
          "url": "https://www.samsung.com/hu/lifestyle-tvs/the-terrace/",
          "analytics": "the terrace",
          "url_name": "The Terrace",
          "children": []
        },
        {
          "node_type": "L1_Product",
          "name": "The Sero",
          "url": "https://www.samsung.com/hu/lifestyle-tvs/the-sero/",
          "analytics": "the sero",
          "url_name": "The Sero",
          "children": []
        },
        {
          "node_type": "L1_Product",
          "name": "Audio eszközök",
          "url": "https://www.samsung.com/hu/audio-devices/all-audio-devices/",
          "analytics": "sound devices",
          "url_name": "Audio eszközök",
          "children": []
        },
        {
          "node_type": "L1_Product",
          "name": "Projektorok",
          "url": "https://www.samsung.com/hu/projectors/all-projectors/",
          "analytics": "projectors",
          "url_name": "Projektorok",
          "children": []
        },
        {
          "node_type": "L1_Product",
          "name": "TV tartozékok",
          "url": "https://www.samsung.com/hu/tv-accessories/all-tv-accessories/",
          "analytics": "tv accessories",
          "url_name": "TV tartozékok",
          "children": []
        },
        {
          "node_type": "L1_Product",
          "name": "Audio tartozékok",
          "url": "https://www.samsung.com/hu/audio-accessories/all-audio-accessories/",
          "analytics": "audio accessories",
          "url_name": "Audio tartozékok",
          "children": []
        },
        {
          "node_type": "L1_Product",
          "name": "TV-k méret szerint",
          "url": "https://www.samsung.com/hu/tvs/98-inch-tvs/",
          "analytics": "tvs by sizes",
          "url_name": "TV-k méret szerint",
          "children": []
        },
        {
          "node_type": "L1_Product",
          "name": "98\"",
          "url": "https://www.samsung.com/hu/tvs/98-inch-tvs/",
          "analytics": "98 inch",
          "url_name": "98\"",
          "children": []
        },
        {
          "node_type": "L1_Product",
          "name": "85\"",
          "url": "https://www.samsung.com/hu/tvs/85-inch-tvs/",
          "analytics": "85 inch",
          "url_name": "85\"",
          "children": []
        },
        {
          "node_type": "L1_Product",
          "name": "75\"",
          "url": "https://www.samsung.com/hu/tvs/75-inch-tvs/",
          "analytics": "75 inch",
          "url_name": "75\"",
          "children": []
        },
        {
          "node_type": "L1_Product",
          "name": "65\"",
          "url": "https://www.samsung.com/hu/tvs/65-inch-tvs/",
          "analytics": "65 inch",
          "url_name": "65\"",
          "children": []
        },
        {
          "node_type": "L1_Product",
          "name": "55\"",
          "url": "https://www.samsung.com/hu/tvs/55-inch-tvs/",
          "analytics": "55 inch",
          "url_name": "55\"",
          "children": []
        },
        {
          "node_type": "L1_Product",
          "name": "50\"",
          "url": "https://www.samsung.com/hu/tvs/50-inch-tvs/",
          "analytics": "50 inch",
          "url_name": "50\"",
          "children": []
        },
        {
          "node_type": "L1_Product",
          "name": "43\"",
          "url": "https://www.samsung.com/hu/tvs/43-inch-tvs/",
          "analytics": "43 inch",
          "url_name": "43\"",
          "children": []
        },
        {
          "node_type": "L1_Product",
          "name": "32\"",
          "url": "https://www.samsung.com/hu/tvs/32-inch-tvs/",
          "analytics": "32 inch or smaller",
          "url_name": "32\"",
          "children": []
        },
        {
          "node_type": "L1_Product",
          "name": "TV-k felbontás szerint",
          "url": "https://www.samsung.com/hu/tvs/8k-tv/",
          "analytics": "tvs by resolution",
          "url_name": "TV-k felbontás szerint",
          "children": []
        },
        {
          "node_type": "L1_Product",
          "name": "8K TV-k",
          "url": "https://www.samsung.com/hu/tvs/8k-tv/",
          "analytics": "8k tvs",
          "url_name": "8K TV-k",
          "children": []
        },
        {
          "node_type": "L1_Product",
          "name": "4K TV-k",
          "url": "https://www.samsung.com/hu/tvs/uhd-4k-tv/",
          "analytics": "4k tvs",
          "url_name": "4K TV-k",
          "children": []
        },
        {
          "node_type": "L1_Product",
          "name": "Full HD/HD TV-k",
          "url": "https://www.samsung.com/hu/tvs/full-hd-tv/",
          "analytics": "full hd hd tvs",
          "url_name": "Full HD/HD TV-k",
          "children": []
        },
        {
          "node_type": "L1_Banner",
          "name": "Samsung Vision AI",
          "url": "www.samsung.com/hu/tvs/vision-ai-tv",
          "analytics": "samsung vision ai",
          "url_name": "Samsung Vision AI",
          "children": []
        },
        {
          "node_type": "L1_Banner",
          "name": "Miért a Samsung TV?",
          "url": "https://www.samsung.com/hu/tvs/why-samsung-tv",
          "analytics": "why samsung tv",
          "url_name": "Miért a Samsung TV?",
          "children": []
        },
        {
          "node_type": "L1_Banner",
          "name": "Miért az OLED?",
          "url": "https://www.samsung.com/hu/tvs/oled-tv/highlights/",
          "analytics": "why oled",
          "url_name": "Miért az OLED?",
          "children": []
        },
        {
          "node_type": "L1_Banner",
          "name": "Miért a Neo QLED?",
          "url": "https://www.samsung.com/hu/tvs/qled-tv/highlights/",
          "analytics": "why neo qled",
          "url_name": "Miért a Neo QLED?",
          "children": []
        },
        {
          "node_type": "L1_Banner",
          "name": "Miért a The Frame?",
          "url": "https://www.samsung.com/hu/lifestyle-tvs/the-frame/highlights/",
          "analytics": "why the frame",
          "url_name": "Miért a The Frame?",
          "children": []
        },
        {
          "node_type": "L1_Banner",
          "name": "Milyen TV-t válasszak?",
          "url": "https://www.samsung.com/hu/tvs/help-me-choose/",
          "analytics": "help choose my tv",
          "url_name": "Milyen TV-t válasszak?",
          "children": []
        },
        {
          "node_type": "L1_Banner",
          "name": "Milyen audio eszközt válasszak?",
          "url": "https://www.samsung.com/hu/audio-devices/help-me-choose/",
          "analytics": "help choose my sound device",
          "url_name": "Milyen audio eszközt válasszak?",
          "children": []
        },
        {
          "node_type": "L1_Banner",
          "name": "MICRO LED",
          "url": "https://www.samsung.com/hu/tvs/micro-led/highlights/",
          "analytics": "micro led",
          "url_name": "MICRO LED",
          "children": []
        }
      ]
    },
    {
      "node_type": "L0",
      "name": "Háztartási gépek",
      "url": "https://www.samsung.com/hu/refrigerators/all-refrigerators/",
      "analytics": "appliances",
      "url_name": "Háztartási gépek",
      "children": [
        {
          "node_type": "L1_Product",
          "name": "Hűtőszekrények",
          "url": "https://www.samsung.com/hu/refrigerators/all-refrigerators/",
          "analytics": "refrigerators",
          "url_name": "Hűtőszekrények",
          "children": []
        },
        {
          "node_type": "L1_Product",
          "name": "Sütők",
          "url": "https://www.samsung.com/hu/cooking-appliances/all-cooking-appliances/?built-in-ovens",
          "analytics": "ovens",
          "url_name": "Sütők",
          "children": []
        },
        {
          "node_type": "L1_Product",
          "name": "Főzőlapok",
          "url": "https://www.samsung.com/hu/cooking-appliances/hobs/",
          "analytics": "hobs",
          "url_name": "Főzőlapok",
          "children": []
        },
        {
          "node_type": "L1_Product",
          "name": "Páraelszívók",
          "url": "https://www.samsung.com/hu/cooking-appliances/hoods/",
          "analytics": "hoods",
          "url_name": "Páraelszívók",
          "children": []
        },
        {
          "node_type": "L1_Product",
          "name": "Mikrohullámú sütők",
          "url": "https://www.samsung.com/hu/microwave-ovens/all-microwave-ovens/",
          "analytics": "microwaves",
          "url_name": "Mikrohullámú sütők",
          "children": []
        },
        {
          "node_type": "L1_Product",
          "name": "Mosogatógépek",
          "url": "https://www.samsung.com/hu/dishwashers/all-dishwashers/",
          "analytics": "dishwashers",
          "url_name": "Mosogatógépek",
          "children": []
        },
        {
          "node_type": "L1_Product",
          "name": "Mosó- és szárítógépek",
          "url": "https://www.samsung.com/hu/washers-and-dryers/all-washers-and-dryers/",
          "analytics": "laundry",
          "url_name": "Mosó- és szárítógépek",
          "children": []
        },
        {
          "node_type": "L1_Product",
          "name": "Jet álló porszívók",
          "url": "https://www.samsung.com/hu/vacuum-cleaners/all-vacuum-cleaners/?stick",
          "analytics": "jet stick vacuums",
          "url_name": "Jet álló porszívók",
          "children": []
        },
        {
          "node_type": "L1_Product",
          "name": "Jet Bot robot porszívók",
          "url": "https://www.samsung.com/hu/vacuum-cleaners/robot/",
          "analytics": "jet bot robot vacuums",
          "url_name": "Jet Bot robot porszívók",
          "children": []
        },
        {
          "node_type": "L1_Product",
          "name": "Légkondicionálók",
          "url": "https://samsung-climatesolutions.com/hu/b2c.html",
          "analytics": "air conditioners",
          "url_name": "Légkondicionálók",
          "children": []
        },
        {
          "node_type": "L1_Product",
          "name": "Air Purifier",
          "url": "https://www.samsung.com/vn/air-care/all-air-care/",
          "analytics": "air purifier",
          "url_name": "Air Purifier",
          "children": []
        },
        {
          "node_type": "L1_Product",
          "name": "Háztartási gép tartozékok",
          "url": "https://www.samsung.com/hu/home-appliance-accessories/all-home-appliance-accessories/",
          "analytics": "appliances accessories",
          "url_name": "Háztartási gép tartozékok",
          "children": []
        },
        {
          "node_type": "L1_Banner",
          "name": "Bespoke AI",
          "url": "https://www.samsung.com/hu/home-appliances/bespoke-home/",
          "analytics": "bespoke ai",
          "url_name": "Bespoke AI",
          "children": []
        },
        {
          "node_type": "L1_Banner",
          "name": "Okos megoldások",
          "url": "https://www.samsung.com/hu/home-appliances/bespoke-ai-smartthings/",
          "analytics": "smart forward",
          "url_name": "Okos megoldások",
          "children": []
        },
        {
          "node_type": "L1_Banner",
          "name": "AI energiatakarékosság",
          "url": "https://www.samsung.com/hu/home-appliances/ai-energy-saving/",
          "analytics": "ai energy saving",
          "url_name": "AI energiatakarékosság",
          "children": []
        },
        {
          "node_type": "L1_Banner",
          "name": "Miért a Samsung háztartási gépek?",
          "url": "https://www.samsung.com/hu/home-appliances/why-samsung-appliances/",
          "analytics": "why samsung appliances",
          "url_name": "Miért a Samsung háztartási gépek?",
          "children": []
        },
        {
          "node_type": "L1_Banner",
          "name": "Hűtőszekrény vásárlási útmutató",
          "url": "https://www.samsung.com/hu/home-appliances/buying-guide/what-is-the-best-type-of-fridge-freezer/",
          "analytics": "refrigerator buying guide",
          "url_name": "Hűtőszekrény vásárlási útmutató",
          "children": []
        },
        {
          "node_type": "L1_Banner",
          "name": "Mosógép vásárlási útmutató",
          "url": "https://www.samsung.com/hu/home-appliances/buying-guide/what-size-washing-machine-do-i-need/",
          "analytics": "laundry buying guide",
          "url_name": "Mosógép vásárlási útmutató",
          "children": []
        },
        {
          "node_type": "L1_Banner",
          "name": "Porszívó vásárlási útmutató",
          "url": "https://www.samsung.com/hu/home-appliances/buying-guide/how-to-choose-a-vacuum-cleaner/",
          "analytics": "vacuum buying guide",
          "url_name": "Porszívó vásárlási útmutató",
          "children": []
        },
        {
          "node_type": "L1_Banner",
          "name": "Háztartási gép vásárlási útmutató",
          "url": "https://www.samsung.com/hu/home-appliances/buying-guide/",
          "analytics": "cooking buying guide",
          "url_name": "Háztartási gép vásárlási útmutató",
          "children": []
        }
      ]
    },
    {
      "node_type": "L0",
      "name": "IT",
      "url": "https://www.samsung.com/hu/monitors/all-monitors/",
      "analytics": "it",
      "url_name": "IT",
      "children": [
        {
          "node_type": "L1_Product",
          "name": "Galaxy Book & Laptop",
          "url": "https://www.samsung.com/uk/computers/all-computers/",
          "analytics": "galaxy book & laptop",
          "url_name": "Galaxy Book & Laptop",
          "children": []
        },
        {
          "node_type": "L1_Product",
          "name": "Monitorok",
          "url": "https://www.samsung.com/hu/monitors/all-monitors/",
          "analytics": "monitors",
          "url_name": "Monitorok",
          "children": []
        },
        {
          "node_type": "L1_Product",
          "name": "Adathordozók",
          "url": "https://www.samsung.com/hu/memory-storage/all-memory-storage/",
          "analytics": "memory & storage",
          "url_name": "Adathordozók",
          "children": []
        },
        {
          "node_type": "L1_Product",
          "name": "Laptop Accessories",
          "url": "https://www.samsung.com/uk/computer-accessories/all-computer-accessories/",
          "analytics": "laptop accessories",
          "url_name": "Laptop Accessories",
          "children": []
        },
        {
          "node_type": "L1_Banner",
          "name": "Copilot+ PCs",
          "url": "https://www.samsung.com/uk/computers/galaxy-book-copilot-plus-pcs/",
          "analytics": "copliot + pcs",
          "url_name": "Copilot+ PCs",
          "children": []
        },
        {
          "node_type": "L1_Banner",
          "name": "Miért az Odyssey gaming monitor?",
          "url": "https://www.samsung.com/hu/monitors/odyssey-gaming-monitor/",
          "analytics": "why odyssey gaming monitor",
          "url_name": "Miért az Odyssey gaming monitor?",
          "children": []
        },
        {
          "node_type": "L1_Banner",
          "name": "Miért a Viewfinity nagy felbontású monitor?",
          "url": "https://www.samsung.com/hu/monitors/high-resolution-monitor/",
          "analytics": "why viewfinity high resolution",
          "url_name": "Miért a Viewfinity nagy felbontású monitor?",
          "children": []
        },
        {
          "node_type": "L1_Banner",
          "name": "Miért a Smart Monitor?",
          "url": "https://www.samsung.com/hu/monitors/smart-monitor/",
          "analytics": "Why Smart Monitor",
          "url_name": "Miért a Smart Monitor?",
          "children": []
        },
        {
          "node_type": "L1_Banner",
          "name": "Help choose my Monitor",
          "url": "https://www.samsung.com/uk/monitors/help-me-choose/",
          "analytics": "Help choose my Monitor",
          "url_name": "Help choose my Monitor",
          "children": []
        },
        {
          "node_type": "L1_Banner",
          "name": "Monitor Buying Guide",
          "url": "https://www.samsung.com/uk/monitors/monitor-buying-guide/",
          "analytics": "Monitor Buying Guide",
          "url_name": "Monitor Buying Guide",
          "children": []
        }
      ]
    },
    {
      "node_type": "L0",
      "name": "Viselhető eszközök",
      "url": "https://www.samsung.com/hu/watches/all-watches/",
      "analytics": "wearables",
      "url_name": "Viselhető eszközök",
      "children": [
        {
          "node_type": "L1_Product",
          "name": "Galaxy Watch",
          "url": "https://www.samsung.com/hu/watches/all-watches/",
          "analytics": "galaxy watch",
          "url_name": "Galaxy Watch",
          "children": []
        },
        {
          "node_type": "L1_Product",
          "name": "Galaxy Buds",
          "url": "https://www.samsung.com/hu/audio-sound/all-audio-sound/",
          "analytics": "galaxy buds",
          "url_name": "Galaxy Buds",
          "children": []
        },
        {
          "node_type": "L1_Product",
          "name": "Galaxy Ring",
          "url": "https://www.samsung.com/hu/rings/all-rings/",
          "analytics": "galaxy ring",
          "url_name": "Galaxy Ring",
          "children": []
        },
        {
          "node_type": "L1_Product",
          "name": "Viselhető eszköz tartozékok",
          "url": "https://www.samsung.com/hu/mobile-accessories/all-mobile-accessories/?watches+audio+smarttag",
          "analytics": "wearables accessories",
          "url_name": "Viselhető eszköz tartozékok",
          "children": []
        },
        {
          "node_type": "L1_Banner",
          "name": "Samsung Health",
          "url": "https://www.samsung.com/hu/apps/samsung-health/",
          "analytics": "samsung health",
          "url_name": "Samsung Health",
          "children": []
        },
        {
          "node_type": "L1_Banner",
          "name": "Galaxy AI",
          "url": "https://www.samsung.com/hu/galaxy-ai/",
          "analytics": "galaxy ai",
          "url_name": "Galaxy AI",
          "children": []
        },
        {
          "node_type": "L1_Banner",
          "name": "Appok és szolgáltatások",
          "url": "https://www.samsung.com/hu/apps/",
          "analytics": "apps & service",
          "url_name": "Appok és szolgáltatások",
          "children": []
        },
        {
          "node_type": "L1_Banner",
          "name": "Miért a Galaxy?",
          "url": "https://www.samsung.com/hu/mobile/why-galaxy/",
          "analytics": "why galaxy",
          "url_name": "Miért a Galaxy?",
          "children": []
        },
        {
          "node_type": "L1_Banner",
          "name": "Válts Galaxyra!",
          "url": "https://www.samsung.com/hu/mobile/switch-to-galaxy/",
          "analytics": "switch to galaxy",
          "url_name": "Válts Galaxyra!",
          "children": []
        },
        {
          "node_type": "L1_Banner",
          "name": "Készülékbeszámítás",
          "url": "https://www.samsung.com/hu/offer/mobile-trade-in/",
          "analytics": "samsung trade-in",
          "url_name": "Készülékbeszámítás",
          "children": []
        }
      ]
    },
    {
      "node_type": "L0",
      "name": "Tartozékok",
      "url": "https://www.samsung.com/hu/accessories/",
      "analytics": "accessories",
      "url_name": "Tartozékok",
      "children": [
        {
          "node_type": "L1_Product",
          "name": "Okostelefon tartozékok",
          "url": "https://www.samsung.com/hu/mobile-accessories/all-mobile-accessories/?smartphones",
          "analytics": "smartphone accessories",
          "url_name": "Okostelefon tartozékok",
          "children": []
        },
        {
          "node_type": "L1_Product",
          "name": "Tablet tartozékok",
          "url": "https://www.samsung.com/hu/mobile-accessories/all-mobile-accessories/?tablets",
          "analytics": "tablet accessories",
          "url_name": "Tablet tartozékok",
          "children": []
        },
        {
          "node_type": "L1_Product",
          "name": "Galaxy Watch tartozékok",
          "url": "https://www.samsung.com/hu/mobile-accessories/all-mobile-accessories/?watches",
          "analytics": "galaxy watch accessories",
          "url_name": "Galaxy Watch tartozékok",
          "children": []
        },
        {
          "node_type": "L1_Product",
          "name": "Galaxy Buds tartozékok",
          "url": "https://www.samsung.com/hu/mobile-accessories/all-mobile-accessories/?audio",
          "analytics": "galaxy buds accessories",
          "url_name": "Galaxy Buds tartozékok",
          "children": []
        },
        {
          "node_type": "L1_Product",
          "name": "Galaxy Book Accessories",
          "url": "https://www.samsung.com/uk/computer-accessories/all-computer-accessories/",
          "analytics": "galaxy book accessories",
          "url_name": "Galaxy Book Accessories",
          "children": []
        },
        {
          "node_type": "L1_Product",
          "name": "SmartTag",
          "url": "https://www.samsung.com/hu/mobile-accessories/all-mobile-accessories/?smarttag",
          "analytics": "smarttag",
          "url_name": "SmartTag",
          "children": []
        },
        {
          "node_type": "L1_Product",
          "name": "TV tartozékok",
          "url": "https://www.samsung.com/hu/tv-accessories/all-tv-accessories/",
          "analytics": "tv accessories",
          "url_name": "TV tartozékok",
          "children": []
        },
        {
          "node_type": "L1_Product",
          "name": "Audio tartozékok",
          "url": "https://www.samsung.com/hu/audio-accessories/all-audio-accessories/",
          "analytics": "audio accessories",
          "url_name": "Audio tartozékok",
          "children": []
        },
        {
          "node_type": "L1_Product",
          "name": "Projektor tartozékok",
          "url": "https://www.samsung.com/hu/tv-accessories/all-tv-accessories/?projector-accessories",
          "analytics": "projector accessories",
          "url_name": "Projektor tartozékok",
          "children": []
        },
        {
          "node_type": "L1_Product",
          "name": "Hűtőszekrény tartozékok",
          "url": "https://www.samsung.com/hu/home-appliance-accessories/all-home-appliance-accessories/?refrigerator",
          "analytics": "refrigerator accessories",
          "url_name": "Hűtőszekrény tartozékok",
          "children": []
        },
        {
          "node_type": "L1_Product",
          "name": "Porszívó tartozékok",
          "url": "https://www.samsung.com/hu/home-appliance-accessories/all-home-appliance-accessories/?vacuum-cleaner",
          "analytics": "vacuum cleaner accessories",
          "url_name": "Porszívó tartozékok",
          "children": []
        },
        {
          "node_type": "L1_Product",
          "name": "Mosó- és szárítógép tartozékok",
          "url": "https://www.samsung.com/hu/home-appliance-accessories/all-home-appliance-accessories/?washer-dryer",
          "analytics": "washer and dryer accessories",
          "url_name": "Mosó- és szárítógép tartozékok",
          "children": []
        }
      ]
    }
  ]
}